[
  {
    "name": "command",
    "optionStyle": "short-and-long",
    "options": [
      {
        "key": "p",
        "title": "-p",
        "description": "use a default value for PATH that is guaranteed to find all of the standard utilities"
      },
      {
        "key": "v",
        "title": "-v",
        "description": "print a description of COMMAND similar to the `type' builtin"
      },
      {
        "key": "V",
        "title": "-V",
        "description": "print a more verbose description of each COMMAND"
      }
    ]
  }
]
