[
  {
    "name": "magick-script",
    "options": [
      {
        "type": "long",
        "key": "adaptive-blur",
        "title": "-adaptive-blur geometry",
        "description": "adaptively blur pixels; decrease effect near edges"
      },
      {
        "type": "long",
        "key": "adaptive-resize",
        "title": "-adaptive-resize geometry",
        "description": "adaptively resize image with data dependent triangulation."
      },
      {
        "type": "long",
        "key": "adaptive-sharpen",
        "title": "-adaptive-sharpen geometry",
        "description": "adaptively sharpen pixels; increase effect near edges"
      },
      {
        "type": "long",
        "key": "adjoin",
        "title": "-adjoin",
        "description": "join images into a single multi-image file"
      },
      {
        "type": "long",
        "key": "affine",
        "title": "-affine matrix",
        "description": "affine transform matrix"
      },
      {
        "type": "long",
        "key": "alpha",
        "title": "-alpha",
        "description": "on, activate, off, deactivate, set, opaque, copy\", transparent, extract, background, or shape the alpha channel"
      },
      {
        "type": "long",
        "key": "annotate",
        "title": "-annotate geometry text",
        "description": "annotate the image with text"
      },
      {
        "type": "long",
        "key": "antialias",
        "title": "-antialias",
        "description": "remove pixel-aliasing"
      },
      {
        "type": "long",
        "key": "append",
        "title": "-append",
        "description": "append an image sequence"
      },
      {
        "type": "long",
        "key": "authenticate",
        "title": "-authenticate value",
        "description": "decipher image with this password"
      },
      {
        "type": "long",
        "key": "auto-gamma",
        "title": "-auto-gamma",
        "description": "automagically adjust gamma level of image"
      },
      {
        "type": "long",
        "key": "auto-level",
        "title": "-auto-level",
        "description": "automagically adjust color levels of image"
      },
      {
        "type": "long",
        "key": "auto-orient",
        "title": "-auto-orient",
        "description": "automagically orient image"
      },
      {
        "type": "long",
        "key": "background",
        "title": "-background color",
        "description": "background color"
      },
      {
        "type": "long",
        "key": "bench",
        "title": "-bench iterations",
        "description": "measure performance"
      },
      {
        "type": "long",
        "key": "bias",
        "title": "-bias value",
        "description": "add bias when convolving an image"
      },
      {
        "type": "long",
        "key": "black-threshold",
        "title": "-black-threshold value",
        "description": "force all pixels below the threshold into black"
      },
      {
        "type": "long",
        "key": "blue-primary",
        "title": "-blue-primary point",
        "description": "chromaticity blue primary point"
      },
      {
        "type": "long",
        "key": "blue-shift",
        "title": "-blue-shift factor",
        "description": "simulate a scene at nighttime in the moonlight"
      },
      {
        "type": "long",
        "key": "blur",
        "title": "-blur geometry",
        "description": "reduce image noise and reduce detail levels"
      },
      {
        "type": "long",
        "key": "border",
        "title": "-border geometry",
        "description": "surround image with a border of color"
      },
      {
        "type": "long",
        "key": "bordercolor",
        "title": "-bordercolor color",
        "description": "border color"
      },
      {
        "type": "long",
        "key": "brightness-contrast",
        "title": "-brightness-contrast geometry",
        "description": "improve brightness / contrast of the image"
      },
      {
        "type": "long",
        "key": "canny",
        "title": "-canny geometry",
        "description": "use a multi-stage algorithm to detect a wide range of edges in the image"
      },
      {
        "type": "long",
        "key": "caption",
        "title": "-caption string",
        "description": "assign a caption to an image"
      },
      {
        "type": "long",
        "key": "cdl",
        "title": "-cdl filename",
        "description": "color correct with a color decision list"
      },
      {
        "type": "long",
        "key": "channel",
        "title": "-channel type",
        "description": "apply option to select image channels"
      },
      {
        "type": "long",
        "key": "charcoal",
        "title": "-charcoal radius",
        "description": "simulate a charcoal drawing"
      },
      {
        "type": "long",
        "key": "chop",
        "title": "-chop geometry",
        "description": "remove pixels from the image interior"
      },
      {
        "type": "long",
        "key": "clamp",
        "title": "-clamp",
        "description": "set each pixel whose value is below zero to zero and any the pixel whose value is above the quantum range to the quantum range (e.g. 65535) otherwise the pixel value remains unchanged."
      },
      {
        "type": "long",
        "key": "clip",
        "title": "-clip",
        "description": "clip along the first path from the 8BIM profile"
      },
      {
        "type": "long",
        "key": "clip-mask",
        "title": "-clip-mask filename",
        "description": "associate clip mask with the image"
      },
      {
        "type": "long",
        "key": "clip-path",
        "title": "-clip-path id",
        "description": "clip along a named path from the 8BIM profile"
      },
      {
        "type": "long",
        "key": "clone",
        "title": "-clone index",
        "description": "clone an image"
      },
      {
        "type": "long",
        "key": "clut",
        "title": "-clut",
        "description": "apply a color lookup table to the image"
      },
      {
        "type": "long",
        "key": "connected-components",
        "title": "-connected-components connectivity",
        "description": "connected-components uniquely labeled, choose from 4 or 8 way connectivity"
      },
      {
        "type": "long",
        "key": "contrast-stretch",
        "title": "-contrast-stretch geometry",
        "description": "improve the contrast in an image by `stretching' the range of intensity value"
      },
      {
        "type": "long",
        "key": "coalesce",
        "title": "-coalesce",
        "description": "merge a sequence of images"
      },
      {
        "type": "long",
        "key": "colorize",
        "title": "-colorize value",
        "description": "colorize the image with the fill color"
      },
      {
        "type": "long",
        "key": "color-matrix",
        "title": "-color-matrix matrix",
        "description": "apply color correction to the image."
      },
      {
        "type": "long",
        "key": "colors",
        "title": "-colors value",
        "description": "preferred number of colors in the image"
      },
      {
        "type": "long",
        "key": "colorspace",
        "title": "-colorspace type",
        "description": "set image colorspace"
      },
      {
        "type": "long",
        "key": "combine",
        "title": "-combine",
        "description": "combine a sequence of images"
      },
      {
        "type": "long",
        "key": "comment",
        "title": "-comment string",
        "description": "annotate image with comment"
      },
      {
        "type": "long",
        "key": "compare",
        "title": "-compare",
        "description": "compare image"
      },
      {
        "type": "long",
        "key": "complexoperator",
        "title": "-complexoperator",
        "description": "perform complex mathematics on an image sequence"
      },
      {
        "type": "long",
        "key": "compose",
        "title": "-compose operator",
        "description": "set image composite operator"
      },
      {
        "type": "long",
        "key": "composite",
        "title": "-composite",
        "description": "composite image"
      },
      {
        "type": "long",
        "key": "compress",
        "title": "-compress type",
        "description": "image compression type"
      },
      {
        "type": "long",
        "key": "contrast",
        "title": "-contrast",
        "description": "enhance or reduce the image contrast"
      },
      {
        "type": "long",
        "key": "convolve",
        "title": "-convolve coefficients",
        "description": "apply a convolution kernel to the image"
      },
      {
        "type": "long",
        "key": "copy",
        "title": "-copy geometry offset",
        "description": "copy pixels from one area of an image to another"
      },
      {
        "type": "long",
        "key": "crop",
        "title": "-crop geometry",
        "description": "crop the image"
      },
      {
        "type": "long",
        "key": "cycle",
        "title": "-cycle amount",
        "description": "cycle the image colormap"
      },
      {
        "type": "long",
        "key": "decipher",
        "title": "-decipher filename",
        "description": "convert cipher pixels to plain"
      },
      {
        "type": "long",
        "key": "debug",
        "title": "-debug events",
        "description": "display copious debugging information"
      },
      {
        "type": "long",
        "key": "define",
        "title": "-define format:option",
        "description": "define one or more image format options"
      },
      {
        "type": "long",
        "key": "deconstruct",
        "title": "-deconstruct",
        "description": "break down an image sequence into constituent parts"
      },
      {
        "type": "long",
        "key": "delay",
        "title": "-delay centiseconds",
        "description": "display the next image after pausing"
      },
      {
        "type": "long",
        "key": "delete",
        "title": "-delete index",
        "description": "delete the image from the image sequence"
      },
      {
        "type": "long",
        "key": "density",
        "title": "-density geometry",
        "description": "horizontal and vertical density of the image"
      },
      {
        "type": "long",
        "key": "depth",
        "title": "-depth value",
        "description": "image depth"
      },
      {
        "type": "long",
        "key": "despeckle",
        "title": "-despeckle",
        "description": "reduce the speckles within an image"
      },
      {
        "type": "long",
        "key": "direction",
        "title": "-direction type",
        "description": "render text right-to-left or left-to-right"
      },
      {
        "type": "long",
        "key": "display",
        "title": "-display server",
        "description": "get image or font from this X server"
      },
      {
        "type": "long",
        "key": "dispose",
        "title": "-dispose method",
        "description": "layer disposal method"
      },
      {
        "type": "long",
        "key": "distribute-cache",
        "title": "-distribute-cache port",
        "description": "launch a distributed pixel cache server"
      },
      {
        "type": "long",
        "key": "distort",
        "title": "-distort type coefficients",
        "description": "distort image"
      },
      {
        "type": "long",
        "key": "dither",
        "title": "-dither  method",
        "description": "apply error diffusion to image"
      },
      {
        "type": "long",
        "key": "draw",
        "title": "-draw string",
        "description": "annotate the image with a graphic primitive"
      },
      {
        "type": "long",
        "key": "duplicate",
        "title": "-duplicate count,indexes",
        "description": "duplicate an image one or more times"
      },
      {
        "type": "long",
        "key": "edge",
        "title": "-edge radius",
        "description": "apply a filter to detect edges in the image"
      },
      {
        "type": "long",
        "key": "emboss",
        "title": "-emboss radius",
        "description": "emboss an image"
      },
      {
        "type": "long",
        "key": "encipher",
        "title": "-encipher filename",
        "description": "convert plain pixels to cipher pixels"
      },
      {
        "type": "long",
        "key": "encoding",
        "title": "-encoding type",
        "description": "text encoding type"
      },
      {
        "type": "long",
        "key": "endian",
        "title": "-endian type",
        "description": "endianness (MSB or LSB) of the image"
      },
      {
        "type": "long",
        "key": "enhance",
        "title": "-enhance",
        "description": "apply a digital filter to enhance a noisy image"
      },
      {
        "type": "long",
        "key": "equalize",
        "title": "-equalize",
        "description": "perform histogram equalization to an image"
      },
      {
        "type": "long",
        "key": "evaluate",
        "title": "-evaluate operator value",
        "description": "evaluate an arithmetic, relational, or logical expression"
      },
      {
        "type": "long",
        "key": "evaluate-sequence",
        "title": "-evaluate-sequence operator",
        "description": "evaluate an arithmetic, relational, or logical expression for an image sequence"
      },
      {
        "type": "long",
        "key": "extent",
        "title": "-extent geometry",
        "description": "set the image size"
      },
      {
        "type": "long",
        "key": "extract",
        "title": "-extract geometry",
        "description": "extract area from image"
      },
      {
        "type": "long",
        "key": "family",
        "title": "-family name",
        "description": "render text with this font family"
      },
      {
        "type": "long",
        "key": "features",
        "title": "-features distance",
        "description": "analyze image features (e.g. contract, correlations, etc.)."
      },
      {
        "type": "long",
        "key": "fft",
        "title": "-fft",
        "description": "implements the discrete Fourier transform (DFT)"
      },
      {
        "type": "long",
        "key": "fill",
        "title": "-fill color",
        "description": "color to use when filling a graphic primitive"
      },
      {
        "type": "long",
        "key": "filter",
        "title": "-filter type",
        "description": "use this filter when resizing an image"
      },
      {
        "type": "long",
        "key": "flatten",
        "title": "-flatten",
        "description": "flatten a sequence of images"
      },
      {
        "type": "long",
        "key": "flip",
        "title": "-flip",
        "description": "flip image in the vertical direction"
      },
      {
        "type": "long",
        "key": "floodfill",
        "title": "-floodfill geometry color",
        "description": "floodfill the image with color"
      },
      {
        "type": "long",
        "key": "flop",
        "title": "-flop",
        "description": "flop image in the horizontal direction"
      },
      {
        "type": "long",
        "key": "font",
        "title": "-font name",
        "description": "render text with this font"
      },
      {
        "type": "long",
        "key": "format",
        "title": "-format string",
        "description": "output formatted image characteristics"
      },
      {
        "type": "long",
        "key": "frame",
        "title": "-frame geometry",
        "description": "surround image with an ornamental border"
      },
      {
        "type": "long",
        "key": "function",
        "title": "-function name",
        "description": "apply a function to the image"
      },
      {
        "type": "long",
        "key": "fuzz",
        "title": "-fuzz distance",
        "description": "colors within this distance are considered equal"
      },
      {
        "type": "long",
        "key": "fx",
        "title": "-fx expression",
        "description": "apply mathematical expression to an image channel(s)"
      },
      {
        "type": "long",
        "key": "gamma",
        "title": "-gamma value",
        "description": "level of gamma correction"
      },
      {
        "type": "long",
        "key": "gaussian-blur",
        "title": "-gaussian-blur geometry",
        "description": "reduce image noise and reduce detail levels"
      },
      {
        "type": "long",
        "key": "geometry",
        "title": "-geometry geometry",
        "description": "preferred size or location of the image"
      },
      {
        "type": "long",
        "key": "gravity",
        "title": "-gravity type",
        "description": "horizontal and vertical text placement"
      },
      {
        "type": "long",
        "key": "grayscale",
        "title": "-grayscale method",
        "description": "convert image to grayscale"
      },
      {
        "type": "long",
        "key": "green-primary",
        "title": "-green-primary point",
        "description": "chromaticity green primary point"
      },
      {
        "type": "long",
        "key": "help",
        "title": "-help",
        "description": "print program options"
      },
      {
        "type": "long",
        "key": "hough-lines",
        "title": "-hough-lines geometry",
        "description": "identify lines in the image"
      },
      {
        "type": "long",
        "key": "identify",
        "title": "-identify",
        "description": "identify the format and characteristics of the image"
      },
      {
        "type": "long",
        "key": "ift",
        "title": "-ift",
        "description": "implements the inverse discrete Fourier transform (DFT)"
      },
      {
        "type": "long",
        "key": "implode",
        "title": "-implode amount",
        "description": "implode image pixels about the center"
      },
      {
        "type": "long",
        "key": "insert",
        "title": "-insert index",
        "description": "insert last image into the image sequence"
      },
      {
        "type": "long",
        "key": "intensity",
        "title": "-intensity method",
        "description": "method to generate an intensity value from a pixel"
      },
      {
        "type": "long",
        "key": "intent",
        "title": "-intent type",
        "description": "type of rendering intent when managing the image color"
      },
      {
        "type": "long",
        "key": "interlace",
        "title": "-interlace type",
        "description": "type of image interlacing scheme"
      },
      {
        "type": "long",
        "key": "interline-spacing",
        "title": "-interline-spacing value",
        "description": "the space between two text lines"
      },
      {
        "type": "long",
        "key": "interpolate",
        "title": "-interpolate method",
        "description": "pixel color interpolation method"
      },
      {
        "type": "long",
        "key": "interword-spacing",
        "title": "-interword-spacing value",
        "description": "the space between two words"
      },
      {
        "type": "long",
        "key": "kerning",
        "title": "-kerning value",
        "description": "the space between two characters"
      },
      {
        "type": "long",
        "key": "kuwahara",
        "title": "-kuwahara geometry",
        "description": "edge preserving noise reduction filter"
      },
      {
        "type": "long",
        "key": "label",
        "title": "-label string",
        "description": "assign a label to an image"
      },
      {
        "type": "long",
        "key": "lat",
        "title": "-lat geometry",
        "description": "local adaptive thresholding"
      },
      {
        "type": "long",
        "key": "layers",
        "title": "-layers method",
        "description": "optimize or compare image layers"
      },
      {
        "type": "long",
        "key": "level",
        "title": "-level value",
        "description": "adjust the level of image contrast"
      },
      {
        "type": "long",
        "key": "limit",
        "title": "-limit type value",
        "description": "pixel cache resource limit"
      },
      {
        "type": "long",
        "key": "linear-stretch",
        "title": "-linear-stretch geometry",
        "description": "linear with saturation histogram stretch"
      },
      {
        "type": "long",
        "key": "liquid-rescale",
        "title": "-liquid-rescale geometry",
        "description": "rescale image with seam-carving"
      },
      {
        "type": "long",
        "key": "list",
        "title": "-list type",
        "description": "Color, Configure, Delegate, Format, Magic, Module, Resource, or Type"
      },
      {
        "type": "long",
        "key": "log",
        "title": "-log format",
        "description": "format of debugging information"
      },
      {
        "type": "long",
        "key": "loop",
        "title": "-loop iterations",
        "description": "add Netscape loop extension to your GIF animation"
      },
      {
        "type": "long",
        "key": "mask",
        "title": "-mask filename",
        "description": "associate a mask with the image"
      },
      {
        "type": "long",
        "key": "mattecolor",
        "title": "-mattecolor color",
        "description": "frame color"
      },
      {
        "type": "long",
        "key": "median",
        "title": "-median radius",
        "description": "apply a median filter to the image"
      },
      {
        "type": "long",
        "key": "mean-shift",
        "title": "-mean-shift geometry",
        "description": "delineate arbitrarily shaped clusters in the image"
      },
      {
        "type": "long",
        "key": "metric",
        "title": "-metric type",
        "description": "measure differences between images with this metric"
      },
      {
        "type": "long",
        "key": "mode",
        "title": "-mode radius",
        "description": "make each pixel the 'predominant color' of the neighborhood"
      },
      {
        "type": "long",
        "key": "modulate",
        "title": "-modulate value",
        "description": "vary the brightness, saturation, and hue"
      },
      {
        "type": "long",
        "key": "moments",
        "title": "-moments",
        "description": "display image moments."
      },
      {
        "type": "long",
        "key": "monitor",
        "title": "-monitor",
        "description": "monitor progress"
      },
      {
        "type": "long",
        "key": "monochrome",
        "title": "-monochrome",
        "description": "transform image to black and white"
      },
      {
        "type": "long",
        "key": "morph",
        "title": "-morph value",
        "description": "morph an image sequence"
      },
      {
        "type": "long",
        "key": "morphology",
        "title": "-morphology method kernel",
        "description": "apply a morphology method to the image"
      },
      {
        "type": "long",
        "key": "motion-blur",
        "title": "-motion-blur geometry",
        "description": "simulate motion blur"
      },
      {
        "type": "long",
        "key": "negate",
        "title": "-negate",
        "description": "replace each pixel with its complementary color"
      },
      {
        "type": "long",
        "key": "noise",
        "title": "-noise radius",
        "description": "add or reduce noise in an image"
      },
      {
        "type": "long",
        "key": "normalize",
        "title": "-normalize",
        "description": "transform image to span the full range of colors"
      },
      {
        "type": "long",
        "key": "opaque",
        "title": "-opaque color",
        "description": "change this color to the fill color"
      },
      {
        "type": "long",
        "key": "ordered-dither",
        "title": "-ordered-dither NxN",
        "description": "ordered dither the image"
      },
      {
        "type": "long",
        "key": "orient",
        "title": "-orient type",
        "description": "image orientation"
      },
      {
        "type": "long",
        "key": "page",
        "title": "-page geometry",
        "description": "size and location of an image canvas (setting)"
      },
      {
        "type": "long",
        "key": "paint",
        "title": "-paint radius",
        "description": "simulate an oil painting"
      },
      {
        "type": "long",
        "key": "perceptible",
        "title": "-perceptible",
        "description": "set each pixel whose value is less than |epsilon| to -epsilon or epsilon (whichever is closer) otherwise the pixel value remains unchanged."
      },
      {
        "type": "long",
        "key": "ping",
        "title": "-ping",
        "description": "efficiently determine image attributes"
      },
      {
        "type": "long",
        "key": "pointsize",
        "title": "-pointsize value",
        "description": "font point size"
      },
      {
        "type": "long",
        "key": "polaroid",
        "title": "-polaroid angle",
        "description": "simulate a Polaroid picture"
      },
      {
        "type": "long",
        "key": "poly",
        "title": "-poly terms",
        "description": "build a polynomial from the image sequence and the corresponding terms (coefficients and degree pairs)."
      },
      {
        "type": "long",
        "key": "posterize",
        "title": "-posterize levels",
        "description": "reduce the image to a limited number of color levels"
      },
      {
        "type": "long",
        "key": "precision",
        "title": "-precision value",
        "description": "set the maximum number of significant digits to be printed"
      },
      {
        "type": "long",
        "key": "preview",
        "title": "-preview type",
        "description": "image preview type"
      },
      {
        "type": "long",
        "key": "print",
        "title": "-print string",
        "description": "interpret string and print to console"
      },
      {
        "type": "long",
        "key": "process",
        "title": "-process image-filter",
        "description": "process the image with a custom image filter"
      },
      {
        "type": "long",
        "key": "profile",
        "title": "-profile filename",
        "description": "add, delete, or apply an image profile"
      },
      {
        "type": "long",
        "key": "quality",
        "title": "-quality value",
        "description": "JPEG/MIFF/PNG compression level"
      },
      {
        "type": "long",
        "key": "quantize",
        "title": "-quantize colorspace",
        "description": "reduce image colors in this colorspace"
      },
      {
        "type": "long",
        "key": "quiet",
        "title": "-quiet",
        "description": "suppress all warning messages"
      },
      {
        "type": "long",
        "key": "radial-blur",
        "title": "-radial-blur angle",
        "description": "radial blur the image"
      },
      {
        "type": "long",
        "key": "raise",
        "title": "-raise value",
        "description": "lighten/darken image edges to create a 3-D effect"
      },
      {
        "type": "long",
        "key": "random-threshold",
        "title": "-random-threshold low,high",
        "description": "random threshold the image"
      },
      {
        "type": "long",
        "key": "red-primary",
        "title": "-red-primary point",
        "description": "chromaticity red primary point"
      },
      {
        "type": "long",
        "key": "regard-warnings",
        "title": "-regard-warnings",
        "description": "pay attention to warning messages."
      },
      {
        "type": "long",
        "key": "region",
        "title": "-region geometry",
        "description": "apply options to a portion of the image"
      },
      {
        "type": "long",
        "key": "remap",
        "title": "-remap filename",
        "description": "transform image colors to match this set of colors"
      },
      {
        "type": "long",
        "key": "render",
        "title": "-render",
        "description": "render vector graphics"
      },
      {
        "type": "long",
        "key": "repage",
        "title": "-repage geometry",
        "description": "size and location of an image canvas"
      },
      {
        "type": "long",
        "key": "resample",
        "title": "-resample geometry",
        "description": "change the resolution of an image"
      },
      {
        "type": "long",
        "key": "resize",
        "title": "-resize geometry",
        "description": "resize the image"
      },
      {
        "type": "long",
        "key": "respect-parentheses",
        "title": "-respect-parentheses",
        "description": "settings remain in effect until parenthesis boundary."
      },
      {
        "type": "long",
        "key": "roll",
        "title": "-roll geometry",
        "description": "roll an image vertically or horizontally"
      },
      {
        "type": "long",
        "key": "rotate",
        "title": "-rotate degrees",
        "description": "apply Paeth rotation to the image"
      },
      {
        "type": "long",
        "key": "sample",
        "title": "-sample geometry",
        "description": "scale image with pixel sampling"
      },
      {
        "type": "long",
        "key": "sampling-factor",
        "title": "-sampling-factor geometry",
        "description": "horizontal and vertical sampling factor"
      },
      {
        "type": "long",
        "key": "scale",
        "title": "-scale geometry",
        "description": "scale the image"
      },
      {
        "type": "long",
        "key": "scene",
        "title": "-scene value",
        "description": "image scene number"
      },
      {
        "type": "long",
        "key": "seed",
        "title": "-seed value",
        "description": "seed a new sequence of pseudo-random numbers"
      },
      {
        "type": "long",
        "key": "segment",
        "title": "-segment values",
        "description": "segment an image"
      },
      {
        "type": "long",
        "key": "selective-blur",
        "title": "-selective-blur geometry",
        "description": "selectively blur pixels within a contrast threshold"
      },
      {
        "type": "long",
        "key": "separate",
        "title": "-separate",
        "description": "separate an image channel into a grayscale image"
      },
      {
        "type": "long",
        "key": "sepia-tone",
        "title": "-sepia-tone threshold",
        "description": "simulate a sepia-toned photo"
      },
      {
        "type": "long",
        "key": "set",
        "title": "-set attribute value",
        "description": "set an image attribute"
      },
      {
        "type": "long",
        "key": "shade",
        "title": "-shade degrees",
        "description": "shade the image using a distant light source"
      },
      {
        "type": "long",
        "key": "shadow",
        "title": "-shadow geometry",
        "description": "simulate an image shadow"
      },
      {
        "type": "long",
        "key": "sharpen",
        "title": "-sharpen geometry",
        "description": "sharpen the image"
      },
      {
        "type": "long",
        "key": "shave",
        "title": "-shave geometry",
        "description": "shave pixels from the image edges"
      },
      {
        "type": "long",
        "key": "shear",
        "title": "-shear geometry",
        "description": "slide one edge of the image along the X or Y axis"
      },
      {
        "type": "long",
        "key": "sigmoidal-contrast",
        "title": "-sigmoidal-contrast geometry",
        "description": "increase the contrast without saturating highlights or shadows"
      },
      {
        "type": "long",
        "key": "smush",
        "title": "-smush offset",
        "description": "smush an image sequence together"
      },
      {
        "type": "long",
        "key": "size",
        "title": "-size geometry",
        "description": "width and height of image"
      },
      {
        "type": "long",
        "key": "sketch",
        "title": "-sketch geometry",
        "description": "simulate a pencil sketch"
      },
      {
        "type": "long",
        "key": "solarize",
        "title": "-solarize threshold",
        "description": "negate all pixels above the threshold level"
      },
      {
        "type": "long",
        "key": "splice",
        "title": "-splice geometry",
        "description": "splice the background color into the image"
      },
      {
        "type": "long",
        "key": "spread",
        "title": "-spread radius",
        "description": "displace image pixels by a random amount"
      },
      {
        "type": "long",
        "key": "statistic",
        "title": "-statistic type geometry",
        "description": "replace each pixel with corresponding statistic from the neighborhood"
      },
      {
        "type": "long",
        "key": "strip",
        "title": "-strip",
        "description": "strip image of all profiles and comments"
      },
      {
        "type": "long",
        "key": "stroke",
        "title": "-stroke color",
        "description": "graphic primitive stroke color"
      },
      {
        "type": "long",
        "key": "strokewidth",
        "title": "-strokewidth value",
        "description": "graphic primitive stroke width"
      },
      {
        "type": "long",
        "key": "stretch",
        "title": "-stretch type",
        "description": "render text with this font stretch"
      },
      {
        "type": "long",
        "key": "style",
        "title": "-style type",
        "description": "render text with this font style"
      },
      {
        "type": "long",
        "key": "swap",
        "title": "-swap indexes",
        "description": "swap two images in the image sequence"
      },
      {
        "type": "long",
        "key": "swirl",
        "title": "-swirl degrees",
        "description": "swirl image pixels about the center"
      },
      {
        "type": "long",
        "key": "synchronize",
        "title": "-synchronize",
        "description": "synchronize image to storage device"
      },
      {
        "type": "long",
        "key": "taint",
        "title": "-taint",
        "description": "mark the image as modified"
      },
      {
        "type": "long",
        "key": "texture",
        "title": "-texture filename",
        "description": "name of texture to tile onto the image background"
      },
      {
        "type": "long",
        "key": "threshold",
        "title": "-threshold value",
        "description": "threshold the image"
      },
      {
        "type": "long",
        "key": "thumbnail",
        "title": "-thumbnail geometry",
        "description": "create a thumbnail of the image"
      },
      {
        "type": "long",
        "key": "tile",
        "title": "-tile filename",
        "description": "tile image when filling a graphic primitive"
      },
      {
        "type": "long",
        "key": "tile-offset",
        "title": "-tile-offset geometry",
        "description": "set the image tile offset"
      },
      {
        "type": "long",
        "key": "tint",
        "title": "-tint value",
        "description": "tint the image with the fill color"
      },
      {
        "type": "long",
        "key": "transform",
        "title": "-transform",
        "description": "affine transform image"
      },
      {
        "type": "long",
        "key": "transparent",
        "title": "-transparent color",
        "description": "make this color transparent within the image"
      },
      {
        "type": "long",
        "key": "transparent-color",
        "title": "-transparent-color color",
        "description": "transparent color"
      },
      {
        "type": "long",
        "key": "transpose",
        "title": "-transpose",
        "description": "flip image in the vertical direction and rotate 90 degrees"
      },
      {
        "type": "long",
        "key": "transverse",
        "title": "-transverse",
        "description": "flop image in the horizontal direction and rotate 270 degrees"
      },
      {
        "type": "long",
        "key": "treedepth",
        "title": "-treedepth value",
        "description": "color tree depth"
      },
      {
        "type": "long",
        "key": "trim",
        "title": "-trim",
        "description": "trim image edges"
      },
      {
        "type": "long",
        "key": "type",
        "title": "-type type",
        "description": "image type"
      },
      {
        "type": "long",
        "key": "undercolor",
        "title": "-undercolor color",
        "description": "annotation bounding box color"
      },
      {
        "type": "long",
        "key": "unique-colors",
        "title": "-unique-colors",
        "description": "discard all but one of any pixel color."
      },
      {
        "type": "long",
        "key": "units",
        "title": "-units type",
        "description": "the units of image resolution"
      },
      {
        "type": "long",
        "key": "unsharp",
        "title": "-unsharp geometry",
        "description": "sharpen the image"
      },
      {
        "type": "long",
        "key": "verbose",
        "title": "-verbose",
        "description": "print detailed information about the image"
      },
      {
        "type": "long",
        "key": "version",
        "title": "-version",
        "description": "print version information"
      },
      {
        "type": "long",
        "key": "view",
        "title": "-view",
        "description": "FlashPix viewing transforms"
      },
      {
        "type": "long",
        "key": "vignette",
        "title": "-vignette geometry",
        "description": "soften the edges of the image in vignette style"
      },
      {
        "type": "long",
        "key": "virtual-pixel",
        "title": "-virtual-pixel method",
        "description": "access method for pixels outside the boundaries of the image"
      },
      {
        "type": "long",
        "key": "wave",
        "title": "-wave geometry",
        "description": "alter an image along a sine wave"
      },
      {
        "type": "long",
        "key": "wavelet-denoise",
        "title": "-wavelet-denoise threshold",
        "description": "removes noise from the image using a wavelet transform"
      },
      {
        "type": "long",
        "key": "weight",
        "title": "-weight type",
        "description": "render text with this font weight"
      },
      {
        "type": "long",
        "key": "white-point",
        "title": "-white-point point",
        "description": "chromaticity white point"
      },
      {
        "type": "long",
        "key": "white-threshold",
        "title": "-white-threshold value",
        "description": "force all pixels above the threshold into white"
      },
      {
        "type": "long",
        "key": "write",
        "title": "-write filename",
        "description": "write images to this file"
      }
    ]
  }
]
